{
    "results_directory_simulation": "../results/hotmobile/dynamic_HVCs",
    "setting_reserved": "MCS2",
    "setting_contention": "MCS2",
    "aggregation_limit": 150,
    "num_UEs": 9,
    "num_packets_per_ue": null,
    "lambda_range_parameters": [[-4.5, -2.26, 30]],
    "num_iterations_contention": [10, 10, 10, 10, 10, 10, 10, 10, 10, 10, 10, 10, 10, 10, 10, 10, 10, 10, 10, 10, 10, 10, 10, 10, 10, 10, 10, 10, 10, 10],
    "num_iterations_arrival": 20,
    "CWmin": 15,
    "CWmax": 1023,
    "start_offset": 10,
    "duration": 10000000,
    "debug_mode": false,
    "schedule_config": {"schedule_name": "dynamic HBC and LLC",
                        "lambda_fraction": 0.05,
                        "lambda_fraction_embb": 1.1,
                        "maximum_urllc_interval": 4000,
                        "urllc_buffer": 100,
                        "urllc_schedule": [["UE0", "UE1", "UE2", "UE3", "UE4", "UE5", "UE6", "UE7", "UE8"]],
                        "embb_schedule": [[]],
                        "delivery_latency_spec": {
                            "SNR": 24,
                            "Bandwidth": 80,
                            "MCS": 7,
                            "PER": 0.1,
                            "payload_size": 964,
                            "aggregation": 150,
                            "delivery_latency_embb": [
                                179.93,
                                194.33,
                                208.73,
                                223.13,
                                237.53,
                                251.93,
                                251.93,
                                266.33,
                                280.73,
                                295.13,
                                309.53,
                                323.93,
                                338.33,
                                338.33,
                                352.73,
                                367.13,
                                381.53,
                                395.93,
                                410.33,
                                424.73,
                                424.73,
                                439.13,
                                453.53,
                                467.93,
                                482.33,
                                496.73,
                                511.13,
                                511.13,
                                525.53,
                                539.93,
                                554.33,
                                568.73,
                                583.13,
                                597.53,
                                597.53,
                                611.93,
                                626.33,
                                640.73,
                                655.13,
                                669.53,
                                683.93,
                                683.93,
                                698.33,
                                712.73,
                                727.13,
                                741.53,
                                755.93,
                                770.33,
                                770.33,
                                784.73,
                                799.13,
                                813.53,
                                827.93,
                                842.33,
                                856.73,
                                856.73,
                                871.13,
                                885.53,
                                899.93,
                                914.33,
                                928.73,
                                928.73,
                                943.13,
                                957.53,
                                971.93,
                                986.33,
                                1000.73,
                                1015.13,
                                1015.13,
                                1029.53,
                                1043.93,
                                1058.33,
                                1072.73,
                                1087.13,
                                1101.53,
                                1101.53,
                                1115.93,
                                1130.33,
                                1144.73,
                                1159.13,
                                1173.53,
                                1187.93,
                                1187.93,
                                1202.33,
                                1216.73,
                                1231.13,
                                1245.53,
                                1259.93,
                                1274.33,
                                1274.33,
                                1288.73,
                                1303.13,
                                1317.53,
                                1331.93,
                                1346.33,
                                1360.73,
                                1360.73,
                                1375.13,
                                1389.53,
                                1403.93,
                                1418.33,
                                1432.73,
                                1447.13,
                                1447.13,
                                1461.53,
                                1475.93,
                                1490.33,
                                1504.73,
                                1519.13,
                                1533.53,
                                1533.53,
                                1547.93,
                                1562.33,
                                1576.73,
                                1591.13,
                                1605.53,
                                1619.93,
                                1619.93,
                                1634.33,
                                1648.73,
                                1663.13,
                                1677.53,
                                1691.93,
                                1691.93,
                                1706.33,
                                1720.73,
                                1735.13,
                                1749.53,
                                1763.93,
                                1778.33,
                                1778.33,
                                1792.73,
                                1807.13,
                                1821.53,
                                1835.93,
                                1850.33,
                                1864.73,
                                1864.73,
                                1879.13,
                                1893.53,
                                1907.93,
                                1922.33,
                                1936.73,
                                1951.13,
                                1951.13,
                                1965.53,
                                1979.93,
                                1994.33,
                                2008.73,
                                2023.13,
                                2037.53,
                                2037.53,
                                2051.93,
                                2066.33,
                                2080.73,
                                2095.13,
                                2109.53,
                                2123.93,
                                2123.93,
                                2138.33,
                                2152.73,
                                2167.13,
                                2181.53,
                                2195.93,
                                2210.33,
                                2210.33,
                                2224.73,
                                2239.13,
                                2253.53,
                                2267.93,
                                2282.33,
                                2296.73,
                                2296.73,
                                2311.13,
                                2325.53,
                                2339.93,
                                2354.33,
                                2368.73,
                                2368.73,
                                2383.13,
                                2397.53,
                                2411.93,
                                2426.33,
                                2440.73,
                                2455.13,
                                2455.13,
                                2469.53,
                                2483.93,
                                2498.33,
                                2512.73,
                                2527.13,
                                2541.53,
                                2541.53,
                                2555.93,
                                2570.33,
                                2584.73,
                                2599.13,
                                2613.53,
                                2627.93,
                                2627.93,
                                2642.33,
                                2656.73,
                                2671.13,
                                2685.53,
                                2699.93,
                                2714.33,
                                2714.33,
                                2728.73,
                                2743.13,
                                2757.53,
                                2771.93,
                                2786.33,
                                2800.73,
                                2800.73,
                                2815.13,
                                2829.53,
                                2843.93,
                                2858.33,
                                2872.73,
                                2887.13,
                                2887.13,
                                2901.53,
                                2915.93,
                                2930.33,
                                2944.73,
                                2959.13,
                                2973.53,
                                2973.53,
                                2987.93,
                                3002.33,
                                3016.73,
                                3031.13,
                                3045.53,
                                3059.93,
                                3059.93,
                                3074.33,
                                3088.73,
                                3103.13,
                                3117.53,
                                3131.93,
                                3131.93,
                                3146.33,
                                3160.73,
                                3175.13,
                                3189.53,
                                3203.93,
                                3218.33,
                                3218.33,
                                3232.73,
                                3247.13,
                                3261.53,
                                3275.93,
                                3290.33,
                                3304.73,
                                3304.73,
                                3319.13,
                                3333.53,
                                3347.93,
                                3362.33,
                                3376.73,
                                3391.13,
                                3391.13,
                                3405.53,
                                3419.93,
                                3434.33,
                                3448.73,
                                3463.13,
                                3477.53,
                                3477.53,
                                3491.93,
                                3506.33,
                                3520.73,
                                3535.13,
                                3549.53,
                                3563.93,
                                3563.93,
                                3578.33,
                                3592.73,
                                3607.13,
                                3621.53,
                                3635.93,
                                3650.33,
                                3650.33,
                                3664.73,
                                3679.13,
                                3693.53,
                                3707.93,
                                3722.33,
                                3736.73,
                                3736.73,
                                3751.13,
                                3765.53,
                                3779.93,
                                3794.33,
                                3808.73,
                                3808.73,
                                3823.13,
                                3837.53,
                                3851.93,
                                3866.33,
                                3880.73,
                                3895.13,
                                3895.13,
                                3909.53,
                                3923.93,
                                3938.33,
                                3952.73,
                                3967.13,
                                3981.53,
                                3981.53,
                                3995.93,
                                4010.33,
                                4024.73,
                                4039.13,
                                4053.53,
                                4067.93,
                                4067.93,
                                4082.33,
                                4096.73,
                                4111.13,
                                4125.53,
                                4139.93,
                                4154.33,
                                4154.33,
                                4168.73,
                                4183.13,
                                4197.53
                            ]
                        }
                        },
    "percentile_to_plot": 99,
    "wifi_slot_time": 9,
    "DIFS": 34,
    "mode_contention": "Mode 4",
    "advance_time": 10
}